Metadata-Version: 2.4
Name: uwqsc-algorithmic-trading
Version: 2025.3.23
Summary: The University of Waterloo quantitative analytics stocks club algorithmic trading repository.
Author-email: Sargun Singh Bhatti <sargunbhatti27@gmail.com>, Param Shah <paramshah07@gmail.com>
Project-URL: Homepage, https://github.com/UWQSC/algorithmic-trading
Classifier: Programming Language :: Python :: 3
Classifier: Operating System :: OS Independent
Classifier: License :: OSI Approved :: MIT License
Requires-Python: >=3.9
License-File: LICENSE.txt
Requires-Dist: matplotlib==3.7.0
Requires-Dist: numpy==1.26.4
Requires-Dist: pandas==2.0.3
Requires-Dist: tensorflow==2.18.0
Requires-Dist: keras==3.8.0
Requires-Dist: torch==2.5.1
Requires-Dist: scikit-learn==1.6.0rc1
Requires-Dist: seaborn==0.13.2
Requires-Dist: statsmodels==0.14.4
Requires-Dist: coverage==7.6.4
Requires-Dist: fastparquet==2024.11.0
Requires-Dist: yfinance==0.2.54
Requires-Dist: setuptools==70.0.0
Requires-Dist: build==1.2.2.post1
Requires-Dist: twine==6.1.0
Dynamic: license-file
